pysonofflanr3/__init__.py
pysonofflanr3/cli.py
pysonofflanr3/client.py
pysonofflanr3/discover.py
pysonofflanr3/sonoffcrypto.py
pysonofflanr3/sonoffdevice.py
pysonofflanr3/sonoffswitch.py
pysonofflanr3/utils.py
pysonofflanr3-1.1.4.dist-info/AUTHORS.rst
pysonofflanr3-1.1.4.dist-info/LICENSE
pysonofflanr3-1.1.4.dist-info/METADATA
pysonofflanr3-1.1.4.dist-info/WHEEL
pysonofflanr3-1.1.4.dist-info/entry_points.txt
pysonofflanr3-1.1.4.dist-info/top_level.txt
pysonofflanr3-1.1.4.dist-info/RECORD
