Metadata-Version: 2.1
Name: pysonofflanr3
Version: 1.1.4
Summary: Interface for Sonoff devices running v3+ Itead firmware.
Home-page: https://github.com/mattsaxon/pysonofflan
Author: Matt Saxon
Author-email: saxonmatt@hotmail.com
License: MIT license
Project-URL: Home Assistant component, https://github.com/mattsaxon/sonoff-lan-mode-homeassistant/
Project-URL: Bug Reports, https://github.com/mattsaxon/pysonofflan/issues/
Project-URL: Component Docs, https://pysonofflanr3.readthedocs.io/
Project-URL: Itead Dev Docs, https://github.com/itead/Sonoff_Devices_DIY_Tools/tree/master/other/
Keywords: pysonofflanr3,homeassistant
Platform: UNKNOWN
Classifier: Development Status :: 4 - Beta
Classifier: Intended Audience :: Developers
Classifier: License :: OSI Approved :: MIT License
Classifier: Natural Language :: English
Classifier: Programming Language :: Python :: 3.6
Classifier: Programming Language :: Python :: 3.7
Classifier: Programming Language :: Python :: 3.8
Classifier: Topic :: Home Automation
Requires-Dist: Click (>=7.0)
Requires-Dist: click-log
Requires-Dist: pycryptodome
Requires-Dist: requests
Requires-Dist: zeroconf (>=0.24.5)
